pepper_cache/__init__.py
pepper_cache/cache.py
pepper_cache-1.3.0.dist-info/LICENSE
pepper_cache-1.3.0.dist-info/METADATA
pepper_cache-1.3.0.dist-info/WHEEL
pepper_cache-1.3.0.dist-info/top_level.txt
pepper_cache-1.3.0.dist-info/RECORD
