Metadata-Version: 2.1
Name: pepper-cache
Version: 1.3.0
Summary: A simple, persistent key/value cache with no dependencies.
Author: depthbomb
Project-URL: Repository, https://github.com/depthbomb/pepper-cache
Project-URL: Issues, https://github.com/depthbomb/pepper-cache/issues
Project-URL: Changelog, https://github.com/depthbomb/pepper-cache/blob/master/CHANGELOG.md
Keywords: cache
Classifier: Development Status :: 5 - Production/Stable
Classifier: Intended Audience :: Developers
Classifier: License :: OSI Approved :: MIT License
Classifier: Natural Language :: English
Classifier: Programming Language :: Python :: 3
Classifier: Programming Language :: Python :: 3.10
Classifier: Programming Language :: Python :: 3.11
Classifier: Topic :: Software Development
Classifier: Topic :: Software Development :: Libraries
Classifier: Topic :: Software Development :: Libraries :: Python Modules
Classifier: Topic :: Utilities
Requires-Python: >=3.10
License-File: LICENSE
